auto_vicuna/__init__.py
auto_vicuna/__main__.py
auto_vicuna/chat.py
auto_vicuna/config.py
auto_vicuna/conversation.py
auto_vicuna/plugins.py
auto_vicuna-0.2.1.dist-info/METADATA
auto_vicuna-0.2.1.dist-info/WHEEL
auto_vicuna-0.2.1.dist-info/entry_points.txt
auto_vicuna-0.2.1.dist-info/licenses/LICENSE
auto_vicuna-0.2.1.dist-info/RECORD
